setup.cfg
setup.py
akira3d/__init__.py
akira3d/camera.py
akira3d/colliders.py
akira3d/createNewGame.py
akira3d/gameEngine.py
akira3d/light.py
akira3d/mesh.py
akira3d/mobs.py
akira3d/model.py
akira3d/phisics.py
akira3d/render.py
akira3d/shader_program.py
akira3d/texture.py
akira3d/vao.py
akira3d/vbo.py
akira3d/vidSys.py
akira3d.egg-info/PKG-INFO
akira3d.egg-info/SOURCES.txt
akira3d.egg-info/dependency_links.txt
akira3d.egg-info/not-zip-safe
akira3d.egg-info/requires.txt
akira3d.egg-info/top_level.txt