Metadata-Version: 2.1
Name: akira3d
Version: 4.8.2
Summary: Modern 3D Graphics Engine by alexCoder23
Author-email: alekseybeldem@gmail.com
